Metadata-Version: 2.1
Name: sphinx-navigation-icons
Version: 0.1
Summary: Add image/font responsive icons to your Sphinx sidebar toctree
Home-page: https://github.com/dgarcia360/sphinx-navigation-icons
Author: David Garcia
Author-email: dgarcia360@outlook.com
License: MIT
Download-URL: http://pypi.python.org/pypi/sphinx-navigation-icons
Platform: any
Classifier: License :: OSI Approved :: MIT License
Classifier: Framework :: Sphinx
Classifier: Framework :: Sphinx :: Extension
Classifier: Topic :: Documentation :: Sphinx
Classifier: Topic :: Software Development :: Documentation
Classifier: Programming Language :: Python :: 2.7
Classifier: Programming Language :: Python :: 3
